{
  "pipeline_info": {
    "execution_time": 12.45,
    "timestamp": "2024-05-21T10:30:00.000000",
    "version": "2.0.0 (Main Agent)",
    "architecture": "Hub-and-Spoke with Main Agent Coordinator",
    "status": "complete",
    "forced_tender_id": null
  },
  "discovery": {
    "total_discovered": 15,
    "sources": {
      "NTPC": 5,
      "POWERGRID": 8,
      "MahaDiscom": 2
    },
    "tenders": [
      {
        "tender_id": "2024_NTPC_101",
        "title": "Supply of 3.3kV XLPE Power Cables for Thermal Power Plant",
        "source": "NTPC",
        "organization": "NTPC Limited",
        "estimated_value": 50000000,
        "deadline": "2024-06-15T00:00:00Z"
      },
      {
        "tender_id": "2024_PG_205",
        "title": "Procurement of Control Cables for Substation Automation",
        "source": "POWERGRID",
        "organization": "Power Grid Corporation of India",
        "estimated_value": 2500000,
        "deadline": "2024-06-20T00:00:00Z"
      },
        {
        "tender_id": "2024_MH_330",
        "title": "Annual Maintenance Contract for Underground Cables",
        "source": "MahaDiscom",
        "organization": "Maharashtra State Electricity Distribution Co.",
        "estimated_value": 1200000,
        "deadline": "2024-05-30T00:00:00Z"
      }
    ]
  },
  "processing": {
    "status": "success",
    "selected_rfp": {
      "tender_id": "2024_NTPC_101",
      "title": "Supply of 3.3kV XLPE Power Cables for Thermal Power Plant",
        "source": "NTPC",
        "organization": "NTPC Limited",
        "estimated_value": 50000000,
        "deadline": "2024-06-15T00:00:00Z"
    },
    "recommendation": "BID",
    "decision": {
      "win_probability": 85.5,
      "quoted_value": 48500000
    },
    "sales_agent_output": {
        "filtering_stats": {
            "total_processed": 15,
            "filtered": 3,
            "qualified": 12
        },
        "selected_rfp_reason": "High value (5Cr), relevant keywords (XLPE, Power Cable), adequate lead time."
    },
    "technical_agent_output": {
      "final_selection": [
        {
          "requirement": "3.3kV 3C x 300 sqmm AL XLPE Cable",
          "selected_sku": "CAB-XLPE-33-3C-300-AL",
          "match_score": 98,
          "description": "Premium Grade XLPE Cable, 3 Core, Aluminum",
          "datasheet_url": "https://example.com/datasheets/cab-xlpe-33.pdf"
        },
        {
            "requirement": "Outdoor Termination Kits for 3.3kV Cable",
             "selected_sku": "ACC-TERM-33-OUT",
             "match_score": 95,
             "description": "Heat Shrink Outdoor Termination Kit"
        }
      ],
      "gaps": []
    },
    "pricing_agent_output": {
      "pricing_details": {
        "total_material_cost": 35000000,
        "total_services_cost": 5000000,
        "taxes": 7200000,
        "margin": 1300000,
        "grand_total": 48500000
      }
    }
  }
}
